supertimer/__init__.py
supertimer/py.typed
supertimer/timer.py
supertimer-0.4.1.dist-info/METADATA
supertimer-0.4.1.dist-info/WHEEL
supertimer-0.4.1.dist-info/licenses/LICENSE
supertimer-0.4.1.dist-info/RECORD
