Metadata-Version: 2.4
Name: supertimer
Version: 0.4.1
Summary: Contextmanager to print or log execution time of code blocks
Project-URL: Homepage, https://github.com/mariushelf/supertimer
Project-URL: Repository, https://github.com/mariushelf/supertimer
Project-URL: Documentation, https://github.com/mariushelf/supertimer
Author-email: Marius Helf <helfsmarius@gmail.com>
License: MIT
License-File: LICENSE
Classifier: Development Status :: 4 - Beta
Classifier: Programming Language :: Python :: 3.9
Classifier: Programming Language :: Python :: 3.10
Classifier: Programming Language :: Python :: 3.11
Classifier: Programming Language :: Python :: 3.12
Classifier: Programming Language :: Python :: 3.13
Classifier: Programming Language :: Python :: Implementation :: PyPy
Classifier: Topic :: System :: Logging
Requires-Python: >=3.9
